setup.py
MARSS/MARSS.py
MARSS/__init__.py
marss-1.0.2.dist-info/licenses/LICENSE
marss-1.0.2.dist-info/METADATA
marss-1.0.2.dist-info/WHEEL
marss-1.0.2.dist-info/top_level.txt
marss-1.0.2.dist-info/RECORD
