Metadata-Version: 2.4
Name: MARSS
Version: 1.0.2
Summary: MARSS is a regression-based method that mitigates an artifactual shared signal between simultaneously acquired slices in unprocessed MB fMRI.
Project-URL: Homepage, https://github.com/CNaP-Lab/MARSS
Project-URL: Issues, https://github.com/CNaP-Lab/MARSS/issues
Classifier: Programming Language :: Python :: 3
Classifier: License :: OSI Approved :: GNU General Public License v3 (GPLv3)
Classifier: Operating System :: OS Independent
Requires-Python: >=3.8
License-File: LICENSE
Requires-Dist: numpy
Requires-Dist: nibabel
Requires-Dist: pandas
Requires-Dist: matplotlib
Requires-Dist: scipy
Requires-Dist: networkx
Requires-Dist: traits
Requires-Dist: python-dateutil
Requires-Dist: traitsui
Requires-Dist: nipype[all]
Requires-Dist: seaborn
Dynamic: license-file
